{
  "date": "2026-05-31",
  "big_problem": "Three Bureau tabs still hide behind HIDDEN_BUREAU_SLUGS while APIs return live league rows — League L5 roster archetypes are invisible in-product.",
  "epic": "League L5 — Unhide remaining Bureau tabs with screenshot-ready renderers",
  "slice_title": "Waiver Tendencies tab unhidden with Hawkeye wire-style renderer",
  "atom_id": "league-waiver-tendencies-tab",
  "parity_ref": "League L5 — hidden Bureau renderers or watermarked export",
  "depth_ref": "League L5",
  "acceptance_ref": "Bureau tab visible; build + pytest PASS",
  "trust_pillars": ["T2", "T5"],
  "allowed_paths": [
    "apps/web/lib/bureau-features.ts",
    "apps/web/components/league/BureauWaiverTendencies.tsx",
    "apps/web/components/league/BureauFeatureBody.tsx"
  ],
  "max_files": 3,
  "max_lines": 200,
  "acceptance_commands": [
    "npm run build --workspace=apps/web",
    "JWT_SECRET=test python3 -m pytest apps/api/tests -q --ignore=apps/api/tests/test_screener_snapshot.py"
  ],
  "out_of_scope": ["schedule tab", "OG cards", "API changes"],
  "builder_mode": "composer-surgical"
}
