{
  "epic_status": "active",
  "big_problem": "Lab OG export cards still mismatch the hero rows users see in-panel — snapshots omit top dynasty assets and read like generic demos.",
  "epic_title": "Lab L5 — OG export cards mirror in-panel live rows",
  "parity_ref": "Explore L5 — Bureau H2H export or Lab panel OG data rows",
  "depth_ref": "Lab L5",
  "atoms": [
    {
      "id": "lab-dashboard-top5-og-snapshot",
      "title": "Dashboard export snapshot uses top5 dynasty assets plus movers",
      "status": "done",
      "merge_commit": null
    },
    {
      "id": "lab-weekly-hot-week-snapshot",
      "title": "Weekly heatmap export snapshot includes hottest week rows",
      "status": "pending",
      "merge_commit": null
    },
    {
      "id": "lab-buysell-combined-snapshot",
      "title": "Buy/sell export snapshot merges buy and sell lanes",
      "status": "pending",
      "merge_commit": null
    },
    {
      "id": "lab-tradevalues-formula-snapshot",
      "title": "Trade values export snapshot uses formula-ranked visible rows",
      "status": "pending",
      "merge_commit": null
    }
  ],
  "next_atom_id": "lab-weekly-hot-week-snapshot",
  "created_at": "2026-05-31T05:48:00Z",
  "updated_at": "2026-05-31T05:48:00Z"
}
