{
  "big_problem": "Lab OG cards still flatten dynasty dashboard into one stat column — exports do not match the Value/Chg rows users see in-panel, so Reddit screenshots look generic.",
  "epic_title": "Lab L5 — OG live panel rows parity",
  "parity_ref": "Lab L5 — OG card per panel matches in-product export",
  "depth_ref": "Lab L5",
  "atoms": [
    {
      "id": "lab-og-dashboard-live-extract",
      "title": "Dashboard OG — live extract mirrors top5 Value + riser Chg rows",
      "status": "done",
      "merge_commit": "1c39d0bd7"
    },
    {
      "id": "lab-og-efficiency-aging-formula-live",
      "title": "Efficiency + Aging OG — formula_score priority on live fetch",
      "status": "done",
      "merge_commit": "a17391fad"
    },
    {
      "id": "lab-og-weekly-prospects-formula-live",
      "title": "Weekly + Prospects OG — formula_score priority on live fetch",
      "status": "done",
      "merge_commit": "65fc0a87b"
    }
  ],
  "next_atom_id": null,
  "epic_status": "complete",
  "created_at": "2026-05-31T13:00:00Z",
  "updated_at": "2026-05-31T11:20:00Z",
  "completed_epics": ["League L5 — Bureau Trade Finder GTM export"]
}
