{
  "epic_status": "active",
  "big_problem": "Lab OG watermarks omit default position filters — breakouts exports click back to an unscoped waiver board.",
  "epic_title": "Lab L5 — OG hallway position defaults (multi-panel)",
  "parity_ref": "Lab L5 — OG card per panel matches in-product export",
  "depth_ref": "Lab L5",
  "atoms": [
    {
      "id": "lab-og-tolab-weekly-position",
      "title": "weekly OG watermark includes default WR position in toLab",
      "status": "done",
      "merge_commit": "9be64d109"
    },
    {
      "id": "lab-og-tolab-efficiency-position",
      "title": "efficiency OG watermark includes default RB position in toLab",
      "status": "done",
      "merge_commit": "8327741"
    },
    {
      "id": "lab-og-tolab-breakouts-position",
      "title": "breakouts OG watermark includes default WR position in toLab",
      "status": "in_progress",
      "merge_commit": null
    }
  ],
  "next_atom_id": "lab-og-tolab-breakouts-position",
  "created_at": "2026-05-31T14:45:00Z",
  "updated_at": "2026-05-31T11:45:00Z",
  "completed_epics": []
}
