{
  "date": "2026-05-31",
  "big_problem": "Five Bureau tabs still hide behind HIDDEN_BUREAU_SLUGS while APIs return live league rows — League L5 depth is invisible in-product (PARITY League L5).",
  "epic": "League L5 — Unhide Bureau tabs with screenshot-ready renderers",
  "atom_id": "league-power-rankings-og",
  "slice_title": "OG share card at /og/power-rankings with demo fallback + Bureau export row",
  "parity_ref": "League L5 — hidden Bureau renderers or watermarked export",
  "depth_ref": "League L5",
  "acceptance_ref": "FACTORY-DOD Gate C2 — power-rankings OG PNG ≥40KB",
  "trust_pillars": ["T2", "T5", "T6"],
  "allowed_paths": [
    "apps/web/app/og/power-rankings/route.tsx",
    "apps/web/components/league/BureauPowerRankingsShareBar.tsx",
    "apps/web/components/league/BureauPowerRankings.tsx"
  ],
  "max_files": 3,
  "max_lines": 280,
  "acceptance_commands": [
    "npm run build --workspace=apps/web",
    "JWT_SECRET=test python3 -m pytest apps/api/tests -q",
    "curl -s -o /tmp/og-pr.png -w '%{http_code} %{size_download}\\n' 'http://localhost:3000/og/power-rankings?download=1&league=test'"
  ],
  "out_of_scope": ["API schema changes", "new npm deps", "NORTH_STAR/DESIGN edits", "other Bureau tabs"],
  "builder_mode": "composer-surgical",
  "votes": {
    "product_strategist": "SHIP",
    "engineering_architect": "SHIP",
    "builder": "SHIP",
    "verdict": "SHIP 3/3"
  }
}
